appstatpy/ExternalFunctions.py
appstatpy/LatexFunctions.py
appstatpy/__init__.py
appstatpy/requirements.txt
appstatpy-0.0.6.dist-info/METADATA
appstatpy-0.0.6.dist-info/WHEEL
appstatpy-0.0.6.dist-info/licenses/LICENSE
appstatpy-0.0.6.dist-info/RECORD
