Metadata-Version: 2.1
Name: appstatpy
Version: 0.0.6
Summary: Utillities package for the course Applied statistics taught at UCPH in the fall of 2023
Author-email: Malthe Nielsen <malthe.nielsen@nbi.ku.dk>
License-File: LICENSE
Classifier: License :: OSI Approved :: MIT License
Classifier: Operating System :: OS Independent
Classifier: Programming Language :: Python :: 3
Requires-Python: >=3.7
